Workbook

Sheet Sheet1
A1: Company_ID | B1: Company_Name | C1: State | D1: Years_Operation | E1: Employees | F1: Annual_Revenue_USD | G1: Profit_Margin_Pct | H1: Debt_to_Equity | I1: Cash_Flow_USD | J1: Loan_Amount_Requested_USD | K1: Monthly_Recycling_Tons | L1: Plant_Utilization_Pct | M1: Collection_Efficiency_Pct | N1: CO2_Saved_Tons | O1: Operational_Cost_USD | P1: Regulatory_Compliance_Score | Q1: Previous_Default | R1: Credit_Score | S1: Risk_Category
A2: C001 | B2: Garcia, Chase and Gonzalez | C2: Colorado | D2: 7 | E2: 108 | F2: 1150819 | G2: 2.87 | H2: 1.01 | I2: 962613 | J2: 211592 | K2: 427 | L2: 62 | M2: 95 | N2: 5653 | O2: 922596 | P2: 62 | Q2: No | R2: 41 | S2: High
A3: C002 | B3: Williams, Morgan and Sanders | C3: Georgia | D3: 18 | E3: 16 | F3: 1554696 | G3: 10.38 | H3: 0.6 | I3: 945913 | J3: 289579 | K3: 894 | L3: 89 | M3: 86 | N3: 6438 | O3: 1255622 | P3: 78 | Q3: Yes | R3: 61 | S3: Medium
A4: C003 | B4: Mullen LLC | C4: Florida | D4: 17 | E4: 71 | F4: 906851 | G4: 16.21 | H4: 0.44 | I4: -15853 | J4: 453959 | K4: 249 | L4: 45 | M4: 65 | N4: 2697 | O4: 691004 | P4: 91 | Q4: Yes | R4: 73 | S4: Medium
A5: C004 | B5: Roberts Ltd | C5: Colorado | D5: 5 | E5: 25 | F5: 2223167 | G5: 11.69 | H5: 0.5 | I5: 948820 | J5: 554422 | K5: 286 | L5: 58 | M5: 83 | N5: 4036 | O5: 1454636 | P5: 76 | Q5: No | R5: 63 | S5: Medium
A6: C005 | B6: Jackson-Dunn | C6: Georgia | D6: 10 | E6: 17 | F6: 4365241 | G6: 14.5 | H6: 0.87 | I6: 855471 | J6: 498575 | K6: 142 | L6: 75 | M6: 89 | N6: 1060 | O6: 2812092 | P6: 100 | Q6: No | R6: 66 | S6: Medium
A7: C006 | B7: Roberts-Sherman | C7: Texas | D7: 20 | E7: 184 | F7: 1686636 | G7: 13.54 | H7: 0.48 | I7: 778316 | J7: 934537 | K7: 1322 | L7: 45 | M7: 89 | N7: 4137 | O7: 1492054 | P7: 73 | Q7: Yes | R7: 64 | S7: Medium
A8: C007 | B8: Kline Inc | C8: New York | D8: 16 | E8: 205 | F8: 1436783 | G8: 10.24 | H8: 0.6 | I8: 296197 | J8: 704901 | K8: 1314 | L8: 78 | M8: 74 | N8: 5477 | O8: 977191 | P8: 61 | Q8: No | R8: 56 | S8: High
A9: C008 | B9: Watson, Moore and Bryant | C9: Ohio | D9: 19 | E9: 172 | F9: 965847 | G9: 5.68 | H9: 1.15 | I9: 32274 | J9: 644095 | K9: 1600 | L9: 85 | M9: 96 | N9: 3849 | O9: 661145 | P9: 99 | Q9: Yes | R9: 52 | S9: High
A10: C009 | B10: Clay, Andersen and Gibson | C10: Texas | D10: 13 | E10: 219 | F10: 1476307 | G10: 5.57 | H10: 0.43 | I10: -7047 | J10: 489277 | K10: 1414 | L10: 54 | M10: 91 | N10: 6744 | O10: 853450 | P10: 76 | Q10: Yes | R10: 59 | S10: High
A11: C010 | B11: Brown-Oliver | C11: Colorado | D11: 17 | E11: 64 | F11: 3337162 | G11: 14.18 | H11: 0.78 | I11: 200931 | J11: 666496 | K11: 480 | L11: 45 | M11: 98 | N11: 7699 | O11: 2961753 | P11: 60 | Q11: Yes | R11: 55 | S11: High
A12: C011 | B12: Baker Ltd | C12: Ohio | D12: 14 | E12: 156 | F12: 2170427 | G12: 24.9 | H12: 0.9 | I12: 897409 | J12: 266833 | K12: 787 | L12: 63 | M12: 88 | N12: 5880 | O12: 1139680 | P12: 98 | Q12: No | R12: 74 | S12: Medium
A13: C012 | B13: Thomas-Ortega | C13: Florida | D13: 2 | E13: 40 | F13: 536057 | G13: 10.79 | H13: 0.14 | I13: 732699 | J13: 848489 | K13: 565 | L13: 61 | M13: 67 | N13: 4689 | O13: 340965 | P13: 71 | Q13: Yes | R13: 68 | S13: Medium
... A501: C500 | B501: Coleman, Harris and Tucker | C501: Arizona | D501: 14 | E501: 133 | F501: 4189505 | G501: 18.1 | H501: 0.17 | I501: 590246 | J501: 455868 | K501: 1431 | L501: 79 | M501: 95 | N501: 3925 | O501: 3873924 | P501: 99 | Q501: Yes | R501: 83 | S501: Low

Sheet Ratio_Analysis
A1: Company_ID | B1: Company_Name | C1: Debt_to_Equity_Ratio | D1: Cash_Flow_to_Loan | E1: Profit_Margin
A2: =Sheet1!A2 -> C001 | B2: =Sheet1!B2 -> Garcia, Chase and Gonzalez | C2: =Sheet1!H2 -> 1.01 | D2: =Sheet1!I2/Sheet1!J2 -> 4.5493828 | E2: =Sheet1!G2 -> 2.87
A3: =Sheet1!A3 -> C002 | B3: =Sheet1!B3 -> Williams, Morgan and Sanders | C3: =Sheet1!H3 -> 0.6 | D3: =Sheet1!I3/Sheet1!J3 -> 3.266511 | E3: =Sheet1!G3 -> 10.38
A4: =Sheet1!A4 -> C003 | B4: =Sheet1!B4 -> Mullen LLC | C4: =Sheet1!H4 -> 0.44 | D4: =Sheet1!I4/Sheet1!J4 -> -0.034921656 | E4: =Sheet1!G4 -> 16.21
A5: =Sheet1!A5 -> C004 | B5: =Sheet1!B5 -> Roberts Ltd | C5: =Sheet1!H5 -> 0.5 | D5: =Sheet1!I5/Sheet1!J5 -> 1.7113679 | E5: =Sheet1!G5 -> 11.69
A6: =Sheet1!A6 -> C005 | B6: =Sheet1!B6 -> Jackson-Dunn | C6: =Sheet1!H6 -> 0.87 | D6: =Sheet1!I6/Sheet1!J6 -> 1.7158321 | E6: =Sheet1!G6 -> 14.5
A7: =Sheet1!A7 -> C006 | B7: =Sheet1!B7 -> Roberts-Sherman | C7: =Sheet1!H7 -> 0.48 | D7: =Sheet1!I7/Sheet1!J7 -> 0.83283594 | E7: =Sheet1!G7 -> 13.54
A8: =Sheet1!A8 -> C007 | B8: =Sheet1!B8 -> Kline Inc | C8: =Sheet1!H8 -> 0.6 | D8: =Sheet1!I8/Sheet1!J8 -> 0.42019659 | E8: =Sheet1!G8 -> 10.24
A9: =Sheet1!A9 -> C008 | B9: =Sheet1!B9 -> Watson, Moore and Bryant | C9: =Sheet1!H9 -> 1.15 | D9: =Sheet1!I9/Sheet1!J9 -> 0.050107515 | E9: =Sheet1!G9 -> 5.68
A10: =Sheet1!A10 -> C009 | B10: =Sheet1!B10 -> Clay, Andersen and Gibson | C10: =Sheet1!H10 -> 0.43 | D10: =Sheet1!I10/Sheet1!J10 -> -0.014402884 | E10: =Sheet1!G10 -> 5.57
A11: =Sheet1!A11 -> C010 | B11: =Sheet1!B11 -> Brown-Oliver | C11: =Sheet1!H11 -> 0.78 | D11: =Sheet1!I11/Sheet1!J11 -> 0.30147368 | E11: =Sheet1!G11 -> 14.18
A12: =Sheet1!A12 -> C011 | B12: =Sheet1!B12 -> Baker Ltd | C12: =Sheet1!H12 -> 0.9 | D12: =Sheet1!I12/Sheet1!J12 -> 3.363186 | E12: =Sheet1!G12 -> 24.9
A13: =Sheet1!A13 -> C012 | B13: =Sheet1!B13 -> Thomas-Ortega | C13: =Sheet1!H13 -> 0.14 | D13: =Sheet1!I13/Sheet1!J13 -> 0.86353388 | E13: =Sheet1!G13 -> 10.79
... A501: =Sheet1!A501 -> C500 | B501: =Sheet1!B501 -> Coleman, Harris and Tucker | C501: =Sheet1!H501 -> 0.17 | D501: =Sheet1!I501/Sheet1!J501 -> 1.2947739 | E501: =Sheet1!G501 -> 18.1

Sheet Credit_Scorecard
A1: Company_ID | B1: Company_Name | C1: Credit_Score | D1: Debt_to_Equity | E1: Regulatory_Compliance | F1: Cash_Flow | G1: Scorecard_Decision
A2: =Sheet1!A2 -> C001 | B2: =Sheet1!B2 -> Garcia, Chase and Gonzalez | C2: =Sheet1!R2 -> 41 | D2: =Sheet1!H2 -> 1.01 | E2: =Sheet1!P2 -> 62 | F2: =Sheet1!I2 -> 962613 | G2: =IF(AND(C2>=70,D2<=1,E2>=60),"Approved",IF(OR(C2<50,D2>2),"Rejected","Manual Review")) -> Rejected
A3: =Sheet1!A3 -> C002 | B3: =Sheet1!B3 -> Williams, Morgan and Sanders | C3: =Sheet1!R3 -> 61 | D3: =Sheet1!H3 -> 0.6 | E3: =Sheet1!P3 -> 78 | F3: =Sheet1!I3 -> 945913 | G3: =IF(AND(C3>=70,D3<=1,E3>=60),"Approved",IF(OR(C3<50,D3>2),"Rejected","Manual Review")) -> Manual Review
A4: =Sheet1!A4 -> C003 | B4: =Sheet1!B4 -> Mullen LLC | C4: =Sheet1!R4 -> 73 | D4: =Sheet1!H4 -> 0.44 | E4: =Sheet1!P4 -> 91 | F4: =Sheet1!I4 -> -15853 | G4: =IF(AND(C4>=70,D4<=1,E4>=60),"Approved",IF(OR(C4<50,D4>2),"Rejected","Manual Review")) -> Approved
A5: =Sheet1!A5 -> C004 | B5: =Sheet1!B5 -> Roberts Ltd | C5: =Sheet1!R5 -> 63 | D5: =Sheet1!H5 -> 0.5 | E5: =Sheet1!P5 -> 76 | F5: =Sheet1!I5 -> 948820 | G5: =IF(AND(C5>=70,D5<=1,E5>=60),"Approved",IF(OR(C5<50,D5>2),"Rejected","Manual Review")) -> Manual Review
A6: =Sheet1!A6 -> C005 | B6: =Sheet1!B6 -> Jackson-Dunn | C6: =Sheet1!R6 -> 66 | D6: =Sheet1!H6 -> 0.87 | E6: =Sheet1!P6 -> 100 | F6: =Sheet1!I6 -> 855471 | G6: =IF(AND(C6>=70,D6<=1,E6>=60),"Approved",IF(OR(C6<50,D6>2),"Rejected","Manual Review")) -> Manual Review
A7: =Sheet1!A7 -> C006 | B7: =Sheet1!B7 -> Roberts-Sherman | C7: =Sheet1!R7 -> 64 | D7: =Sheet1!H7 -> 0.48 | E7: =Sheet1!P7 -> 73 | F7: =Sheet1!I7 -> 778316 | G7: =IF(AND(C7>=70,D7<=1,E7>=60),"Approved",IF(OR(C7<50,D7>2),"Rejected","Manual Review")) -> Manual Review
A8: =Sheet1!A8 -> C007 | B8: =Sheet1!B8 -> Kline Inc | C8: =Sheet1!R8 -> 56 | D8: =Sheet1!H8 -> 0.6 | E8: =Sheet1!P8 -> 61 | F8: =Sheet1!I8 -> 296197 | G8: =IF(AND(C8>=70,D8<=1,E8>=60),"Approved",IF(OR(C8<50,D8>2),"Rejected","Manual Review")) -> Manual Review
A9: =Sheet1!A9 -> C008 | B9: =Sheet1!B9 -> Watson, Moore and Bryant | C9: =Sheet1!R9 -> 52 | D9: =Sheet1!H9 -> 1.15 | E9: =Sheet1!P9 -> 99 | F9: =Sheet1!I9 -> 32274 | G9: =IF(AND(C9>=70,D9<=1,E9>=60),"Approved",IF(OR(C9<50,D9>2),"Rejected","Manual Review")) -> Manual Review
A10: =Sheet1!A10 -> C009 | B10: =Sheet1!B10 -> Clay, Andersen and Gibson | C10: =Sheet1!R10 -> 59 | D10: =Sheet1!H10 -> 0.43 | E10: =Sheet1!P10 -> 76 | F10: =Sheet1!I10 -> -7047 | G10: =IF(AND(C10>=70,D10<=1,E10>=60),"Approved",IF(OR(C10<50,D10>2),"Rejected","Manual Review")) -> Manual Review
A11: =Sheet1!A11 -> C010 | B11: =Sheet1!B11 -> Brown-Oliver | C11: =Sheet1!R11 -> 55 | D11: =Sheet1!H11 -> 0.78 | E11: =Sheet1!P11 -> 60 | F11: =Sheet1!I11 -> 200931 | G11: =IF(AND(C11>=70,D11<=1,E11>=60),"Approved",IF(OR(C11<50,D11>2),"Rejected","Manual Review")) -> Manual Review
A12: =Sheet1!A12 -> C011 | B12: =Sheet1!B12 -> Baker Ltd | C12: =Sheet1!R12 -> 74 | D12: =Sheet1!H12 -> 0.9 | E12: =Sheet1!P12 -> 98 | F12: =Sheet1!I12 -> 897409 | G12: =IF(AND(C12>=70,D12<=1,E12>=60),"Approved",IF(OR(C12<50,D12>2),"Rejected","Manual Review")) -> Approved
A13: =Sheet1!A13 -> C012 | B13: =Sheet1!B13 -> Thomas-Ortega | C13: =Sheet1!R13 -> 68 | D13: =Sheet1!H13 -> 0.14 | E13: =Sheet1!P13 -> 71 | F13: =Sheet1!I13 -> 732699 | G13: =IF(AND(C13>=70,D13<=1,E13>=60),"Approved",IF(OR(C13<50,D13>2),"Rejected","Manual Review")) -> Manual Review
... A501: =Sheet1!A501 -> C500 | B501: =Sheet1!B501 -> Coleman, Harris and Tucker | C501: =Sheet1!R501 -> 83 | D501: =Sheet1!H501 -> 0.17 | E501: =Sheet1!P501 -> 99 | F501: =Sheet1!I501 -> 590246 | G501: =IF(AND(C501>=70,D501<=1,E501>=60),"Approved",IF(OR(C501<50,D501>2),"Rejected","Manual Review")) -> Approved

Sheet Sensitivity_Analysis
A1: Debt_to_Equity_Threshold | B1: Approval_Rate
A2: 0.5 | B2: =COUNTIFS(Credit_Scorecard!C:C,">=70",Credit_Scorecard!D:D,"<="&A2,Credit_Scorecard!E:E,">=60")/COUNTA(Credit_Scorecard!C2:C501) -> 0.202
A3: 0.75 | B3: =COUNTIFS(Credit_Scorecard!C:C,">=70",Credit_Scorecard!D:D,"<="&A3,Credit_Scorecard!E:E,">=60")/COUNTA(Credit_Scorecard!C3:C502) -> 0.24048096
A4: 1 | B4: =COUNTIFS(Credit_Scorecard!C:C,">=70",Credit_Scorecard!D:D,"<="&A4,Credit_Scorecard!E:E,">=60")/COUNTA(Credit_Scorecard!C4:C503) -> 0.25903614
A5: 1.25 | B5: =COUNTIFS(Credit_Scorecard!C:C,">=70",Credit_Scorecard!D:D,"<="&A5,Credit_Scorecard!E:E,">=60")/COUNTA(Credit_Scorecard!C5:C504) -> 0.25955734
A6: 1.5 | B6: =COUNTIFS(Credit_Scorecard!C:C,">=70",Credit_Scorecard!D:D,"<="&A6,Credit_Scorecard!E:E,">=60")/COUNTA(Credit_Scorecard!C6:C505) -> 0.26008065
A7: 1.75 | B7: =COUNTIFS(Credit_Scorecard!C:C,">=70",Credit_Scorecard!D:D,"<="&A7,Credit_Scorecard!E:E,">=60")/COUNTA(Credit_Scorecard!C7:C506) -> 0.26060606
A8: 2 | B8: =COUNTIFS(Credit_Scorecard!C:C,">=70",Credit_Scorecard!D:D,"<="&A8,Credit_Scorecard!E:E,">=60")/COUNTA(Credit_Scorecard!C8:C507) -> 0.2611336
A9: 2.25 | B9: =COUNTIFS(Credit_Scorecard!C:C,">=70",Credit_Scorecard!D:D,"<="&A9,Credit_Scorecard!E:E,">=60")/COUNTA(Credit_Scorecard!C9:C508) -> 0.26166329
A10: 2.5 | B10: =COUNTIFS(Credit_Scorecard!C:C,">=70",Credit_Scorecard!D:D,"<="&A10,Credit_Scorecard!E:E,">=60")/COUNTA(Credit_Scorecard!C10:C509) -> 0.26219512
A11: 3 | B11: =COUNTIFS(Credit_Scorecard!C:C,">=70",Credit_Scorecard!D:D,"<="&A11,Credit_Scorecard!E:E,">=60")/COUNTA(Credit_Scorecard!C11:C510) -> 0.26272912

Sheet Dashboard
A1: Waste-to-Wealth Credit Optimizer
A2: Credit Risk & Sustainability Dashboard
B5: Total Companies | C5: =COUNTA(Credit_Scorecard!A2:A501) -> 500 | I5: Avg Credit Score | J5: =AVERAGE(Credit_Scorecard!C2:C501) -> 63.554
B6: Approval Rate | C6: =COUNTIF(Credit_Scorecard!G:G,"Approved")/COUNTA(Credit_Scorecard!A2:A501) -> 0.258 | I6: Avg CO2 Saved (Approved) | J6: =AVERAGEIF(Credit_Scorecard!G:G,"Approved",Sheet1!N2:N501) -> 4275.5859
B10: Risk_Category | C10: Count | I10: Risk_Category | J10: Avg_CO2_Saved
B11: Approved | C11: =COUNTIF(Credit_Scorecard!G:G,"Approved") -> 129 | I11: Approved | J11: =AVERAGEIF(Credit_Scorecard!G:G,"Approved",Sheet1!N2:N501) -> 4275.5859
B12: Manual Review | C12: =COUNTIF(Credit_Scorecard!G:G,"Manual Review") -> 339 | I12: Manual Review | J12: =AVERAGEIF(Credit_Scorecard!G:G,"Manual Review",Sheet1!N2:N501) -> 4275.2714
B13: Rejected | C13: =COUNTIF(Credit_Scorecard!G:G,"Rejected") -> 32 | I13: Rejected | J13: =AVERAGEIF(Credit_Scorecard!G:G,"Rejected",Sheet1!N2:N501) -> 4451.7188
